kalabash_contacts/__init__.py
kalabash_contacts/apps.py
kalabash_contacts/constants.py
kalabash_contacts/factories.py
kalabash_contacts/forms.py
kalabash_contacts/handlers.py
kalabash_contacts/kbash_extension.py
kalabash_contacts/mocks.py
kalabash_contacts/models.py
kalabash_contacts/serializers.py
kalabash_contacts/settings.py
kalabash_contacts/tasks.py
kalabash_contacts/tests.py
kalabash_contacts/urls.py
kalabash_contacts/urls_api.py
kalabash_contacts/views.py
kalabash_contacts/viewsets.py
kalabash_contacts/importer/__init__.py
kalabash_contacts/importer/backends/__init__.py
kalabash_contacts/importer/backends/outlook.py
kalabash_contacts/lib/__init__.py
kalabash_contacts/lib/carddav.py
kalabash_contacts/locale/br/LC_MESSAGES/django.mo
kalabash_contacts/locale/br/LC_MESSAGES/django.po
kalabash_contacts/locale/en/LC_MESSAGES/django.mo
kalabash_contacts/locale/en/LC_MESSAGES/django.po
kalabash_contacts/locale/es/LC_MESSAGES/django.mo
kalabash_contacts/locale/es/LC_MESSAGES/django.po
kalabash_contacts/locale/fr/LC_MESSAGES/django.mo
kalabash_contacts/locale/fr/LC_MESSAGES/django.po
kalabash_contacts/locale/it/LC_MESSAGES/django.mo
kalabash_contacts/locale/it/LC_MESSAGES/django.po
kalabash_contacts/locale/pl_PL/LC_MESSAGES/django.mo
kalabash_contacts/locale/pl_PL/LC_MESSAGES/django.po
kalabash_contacts/management/__init__.py
kalabash_contacts/management/commands/__init__.py
kalabash_contacts/management/commands/import_contacts.py
kalabash_contacts/migrations/0001_initial.py
kalabash_contacts/migrations/0002_auto_20180124_2311.py
kalabash_contacts/migrations/0003_auto_20181005_1415.py
kalabash_contacts/migrations/0004_auto_20181005_1415.py
kalabash_contacts/migrations/0005_auto_20181005_1445.py
kalabash_contacts/migrations/0006_alter_phonenumber_type.py
kalabash_contacts/migrations/0007_alter_contact_address.py
kalabash_contacts/migrations/__init__.py
kalabash_contacts/static/index.html
kalabash_contacts/static/kalabash_contacts/webpack-stats.json
kalabash_contacts-0.9.2.dist-info/LICENSE
kalabash_contacts-0.9.2.dist-info/METADATA
kalabash_contacts-0.9.2.dist-info/WHEEL
kalabash_contacts-0.9.2.dist-info/top_level.txt
kalabash_contacts-0.9.2.dist-info/RECORD
