Metadata-Version: 2.1
Name: kalabash-contacts
Version: 0.9.2
Summary: Address book for Kalabash
Home-page: https://alphamonak.com/
Author: Alphamonak Solutions
Author-email: amonak@alphamonak.com
License: MIT
Keywords: email
Platform: UNKNOWN
Classifier: Development Status :: 5 - Production/Stable
Classifier: Environment :: Web Environment
Classifier: Framework :: Django :: 2.2
Classifier: Intended Audience :: System Administrators
Classifier: License :: OSI Approved :: MIT License
Classifier: Operating System :: OS Independent
Classifier: Programming Language :: Python :: 3
Classifier: Programming Language :: Python :: 3.8
Classifier: Programming Language :: Python :: 3.9
Classifier: Programming Language :: Python :: 3.10
Classifier: Programming Language :: Python :: 3.11
Classifier: Topic :: Communications :: Email
Classifier: Topic :: Internet :: WWW/HTTP
License-File: LICENSE
Requires-Dist: django-webpack-loader (==2.0.1)
Requires-Dist: vobject
Requires-Dist: lxml (==4.9.4)
Requires-Dist: caldav (==1.3.9)
